.gitignore
.travis.yml
LICENSE
README.md
mkdocs.yml
requirements-test.txt
requirements.txt
setup.py
chariot/__init__.py
chariot/base_dataset_preprocessor.py
chariot/dataset_preprocessor.py
chariot/language_model_preprocessor.py
chariot/preprocessor.py
chariot/storage.py
chariot/util.py
chariot.egg-info/PKG-INFO
chariot.egg-info/SOURCES.txt
chariot.egg-info/dependency_links.txt
chariot.egg-info/requires.txt
chariot.egg-info/top_level.txt
chariot/resource/__init__.py
chariot/resource/data_file.py
chariot/resource/word_vector.py
chariot/transformer/__init__.py
chariot/transformer/base_preprocessor.py
chariot/transformer/vocabulary.py
chariot/transformer/formatter/__init__.py
chariot/transformer/formatter/base.py
chariot/transformer/formatter/categorical_label.py
chariot/transformer/formatter/padding.py
chariot/transformer/generator/__init__.py
chariot/transformer/generator/base.py
chariot/transformer/generator/source_generator.py
chariot/transformer/generator/target_generator.py
chariot/transformer/text/__init__.py
chariot/transformer/text/base.py
chariot/transformer/text/lower_normalizer.py
chariot/transformer/text/regular_expression_replacer.py
chariot/transformer/text/symbol_filter.py
chariot/transformer/text/unicode_normalizer.py
chariot/transformer/token/__init__.py
chariot/transformer/token/base.py
chariot/transformer/token/base_form_normalizer.py
chariot/transformer/token/number_normalizer.py
chariot/transformer/token/stopword_filter.py
chariot/transformer/token/word_frequency_filter.py
chariot/transformer/tokenizer/__init__.py
chariot/transformer/tokenizer/ja_tokenizer.py
chariot/transformer/tokenizer/spacy_tokenizer.py
chariot/transformer/tokenizer/split_tokenizer.py
chariot/transformer/tokenizer/token.py
chariot/visualization/.gitkeep
docs/index.md
docs/css/extra.css
docs/custom_theme/main.html
docs/images/1_prepare_dataset.PNG
docs/images/2_build_and_run.PNG
docs/images/3_format_batch.PNG
docs/images/chariot_feature.gif
docs/images/chariot_flow.png
docs/tutorial/install.md
docs/tutorial/make_custom_preprocessor.md
docs/tutorial/make_preprocessor.md
docs/tutorial/make_preprocessor_pipeline.md
