Metadata-Version: 2.1
Name: chariot
Version: 0.5.5
Summary: Deliver the ready-to-train data to your NLP model.
Home-page: https://github.com/chakki-works/chariot
Author: icoxfog417
Author-email: icoxfog417@yahoo.co.jp
License: Apache License 2.0
Keywords: machine learning,nlp,natural language processing
Platform: UNKNOWN
